{
	"name": "Monokai",
	"version": "1.3.4",
	"description": "A smooth, dusky scheme",
	"originator": "Xamarin Inc. (http://xamarin.com)",

	"palette": [
		{ "name": "monokai-white", "value": "#F8F8F2" },
		{ "name": "monokai-selection", "value": "#49483E" },
		{ "name": "monokai-background", "value": "#272822" },
		{ "name": "monokai-comment", "value": "#75715E" },
		{ "name": "monokai-string", "value": "#E6DB74" },
		{ "name": "monokai-constant", "value": "#AE81FF" },
		{ "name": "monokai-keyword", "value": "#F92672" },
		{ "name": "monokai-type", "value": "#66d9ef" },
		{ "name": "monokai-classname", "value": "#A6E22E" },
		{ "name": "monokai-functionargument", "value": "#FD971F" },
		{ "name": "monokai-invalid", "value": "#F8F8F0" },
		{ "name": "monokai-invalidBackground", "value": "#F92672" },
		{ "name": "skyblue1", "value": "#729fcf" },
		{ "name": "chameleon1", "value": "#8ae234" },
		{ "name": "chameleon2", "value": "#73d216" },
		{ "name": "chameleon3", "value": "#4e9a06" },
		{ "name": "orange1", "value": "#fcaf3e" },
		{ "name": "orange2", "value": "#f57900" },
		{ "name": "plum1", "value": "#ad7fa8" }
	],

	"colors": [
		{ "name": "Background(Read Only)", "color": "#252620" },

		{ "name": "Search result background", "color": "#006060" },
		{ "name": "Search result background (highlighted)", "color": "#008080" },

		{ "name": "Column Ruler", "color": "#393933" },

		{ "name": "Fold Square", "color": "monokai-comment", "secondcolor": "monokai-background" },
		{ "name": "Fold Cross", "color": "#8f8c7e", "secondcolor": "monokai-background" },

		{ "name": "Indentation Guide", "color": "monokai-comment" },

		{ "name": "Indicator Margin", "color": "#3B3A32" },
		{ "name": "Indicator Margin(Separator)", "color": "#3B3A32" },

		{ "name": "Tooltip Pager Top", "color": "#757575" },
		{ "name": "Tooltip Pager Triangle", "color": "#ffffff" },
		{ "name": "Tooltip Pager Text", "color": "#ffffff" },

		{ "name": "Notification Border", "color": "#989892" },

		{ "name": "Completion Window", "color": "monokai-background", "bordercolor": "#989892" },
		{ "name": "Completion Tooltip Window", "color": "#272725", "bordercolor": "#989892" },
		{ "name": "Completion Selection Bar Border", "color": "monokai-selection" },
		{ "name": "Completion Selection Bar Border(Inactive)", "color": "#383830" },
		{ "name": "Completion Selection Bar Background", "color": "monokai-selection", "secondcolor": "monokai-selection" },
		{ "name": "Completion Selection Bar Background(Inactive)", "color": "#383830", "secondcolor": "#383830" },

		{ "name": "Bookmarks", "color": "#FDD99B", "secondcolor": "#816647" },

		{ "name": "Underline(Error)", "color": "red" },
		{ "name": "Underline(Warning)", "color": "skyblue1" },
		{ "name": "Underline(Suggestion)", "color": "chameleon3" },
		{ "name": "Underline(Hint)", "color": "chameleon1" },

		{ "name": "Quick Diff(Dirty)", "color": "monokai-string" },
		{ "name": "Quick Diff(Changed)", "color": "#A4E22E" },

		{ "name": "Brace Matching(Rectangle)", "color": "#517297", "secondcolor": "#517297" },
		{ "name": "Usages(Rectangle)", "color": "#527F99", "secondcolor": "#527F99", "bordercolor": "#527F99" },
		{ "name": "Changing usages(Rectangle)", "color": "#996E75", "secondcolor": "#996E75", "bordercolor": "#996E75" },

		{ "name": "Breakpoint Marker", "color": "#6f3535", "bordercolor": "#6f3535" },
		{ "name": "Breakpoint Marker(Disabled)", "color": "#4d4d4d", "bordercolor": "#4d4d4d" },
		{ "name": "Breakpoint Marker(Invalid)", "color": "#604343", "bordercolor": "#604343" },

		{ "name": "Current Line Marker", "color": "#393933", "secondcolor": "#393933" },
		{ "name": "Current Line Marker(Inactive)", "color": "#393933", "secondcolor": "#393933" },

		{ "name": "Debugger Current Line Marker", "color": "#69684c", "bordercolor": "#69684c" },
		{ "name": "Debugger Stack Line Marker", "color": "#618336", "bordercolor": "#618336" },

		{ "name": "Primary Link", "color": "monokai-white", "secondcolor": "#7f4a81" },
		{ "name": "Primary Link(Highlighted)", "color": "monokai-white", "secondcolor": "#b167b3" },
		{ "name": "Secondary Link", "color": "monokai-white", "secondcolor": "#262228" },
		{ "name": "Secondary Link(Highlighted)", "color": "monokai-white", "secondcolor": "#4e4552" },

		{ "name": "Message Bubble Error Marker", "color": "#b28d37" },
		{ "name": "Message Bubble Error Tag", "color": "#e3a6a1", "secondcolor": "black" },
		{ "name": "Message Bubble Error Counter", "color": "black", "secondcolor": "#e3a6a1" },
		{ "name": "Message Bubble Error IconMargin", "color": "#735c54", "bordercolor": "#805b4d" },
		{ "name": "Message Bubble Error Line", "color": "#7b645c" },
		{ "name": "Message Bubble Error Tooltip", "color": "#e3a6a1" },

		{ "name": "Message Bubble Warning Tag", "color": "#efe89d", "secondcolor": "black" },
		{ "name": "Message Bubble Warning Counter", "color": "black", "secondcolor": "#efe89d" },
		{ "name": "Message Bubble Warning IconMargin", "color": "#777553", "bordercolor": "#948e51" },
		{ "name": "Message Bubble Warning Line", "color": "#807e5c" },
		{ "name": "Message Bubble Warning Tooltip", "color": "#efe89d" },

		{ "name": "Link Color", "color": "#41e2cb" },
		{ "name": "Link Color(Active)", "color": "#41e2cb" }
	],

	"text": [
		{ "name": "Plain Text", "fore": "monokai-white", "back": "monokai-background" },
		{ "name": "Selected Text", "back": "monokai-selection" },
		{ "name": "Selected Text(Inactive)", "back": "#383830" },

		{ "name": "Collapsed Text", "fore": "monokai-comment", "back": "monokai-background" },

		{ "name": "Line Numbers", "fore": "#BCBCBC", "back": "monokai-background" },

		{ "name": "Punctuation", "fore": "monokai-white" },
		{ "name": "Punctuation(Brackets)", "fore": "monokai-white" },

		{ "name": "Comment(Line)", "fore": "monokai-comment" },
		{ "name": "Comment(Block)", "fore": "monokai-comment" },
		{ "name": "Comment(Doc)", "fore": "#617e52" },
		{ "name": "Comment(DocTag)", "fore": "#817235" },
		{ "name": "Comment Tag", "fore": "#ff0dff" },

		{ "name": "Excluded Code", "fore": "monokai-comment" },

		{ "name": "String", "fore": "monokai-string" },
		{ "name": "String(Escape)", "fore": "#A6AB34" },
		{ "name": "String(C# @ Verbatim)", "fore": "monokai-string" },
		{ "name": "String(Regex Set Constructs)", "fore": "chameleon2" },
		{ "name": "String(Regex Character Class)", "fore": "skyblue1" },
		{ "name": "String(Regex Grouping Constructs)", "fore": "plum1" },
		{ "name": "String(Regex Escape Character)", "fore": "orange2" },
		{ "name": "String(Regex Alt Escape Character)", "fore": "orange1" },

		{ "name": "Number", "fore": "monokai-constant" },

		{ "name": "Preprocessor", "fore": "monokai-classname" },
		{ "name": "Preprocessor(Region Name)", "fore": "monokai-classname" },

		{ "name": "Xml Text", "fore": "monokai-white" },
		{ "name": "Xml Delimiter", "fore": "monokai-white" },
		{ "name": "Xml Name", "fore": "monokai-keyword" },
		{ "name": "Xml Attribute", "fore": "monokai-white" },
		{ "name": "Xml Attribute Quotes", "fore": "monokai-string" },
		{ "name": "Xml Attribute Value", "fore": "monokai-string" },
		{ "name": "Xml Comment", "fore": "monokai-comment" },
		{ "name": "Xml CData Section", "fore": "monokai-white" },

		{ "name": "Html Attribute Name", "fore": "monokai-white" },
		{ "name": "Html Attribute Value", "fore": "monokai-string" },
		{ "name": "Html Comment", "fore": "monokai-comment" },
		{ "name": "Html Element Name", "fore": "monokai-keyword" },
		{ "name": "Html Entity", "fore": "monokai-classname" },
		{ "name": "Html Operator", "fore": "monokai-keyword" },
		{ "name": "Html Server-Side Script", "fore": "monokai-white", "back": "#373832" },
		{ "name": "Html Tag Delimiter", "fore": "monokai-white" },
		{ "name": "Razor Code", "fore": "monokai-white", "back": "#373832" },

		{ "name": "Tooltip Text", "fore": "#d1d1cd", "back": "#525759" },
		{ "name": "Notification Text", "fore": "monokai-white", "back": "#272725" },

		{ "name": "Completion Text", "fore": "monokai-white" },
		{ "name": "Completion Matching Substring", "fore": "monokai-keyword" },

		{ "name": "Completion Selected Text", "fore": "monokai-white" },
		{ "name": "Completion Selected Matching Substring", "fore": "monokai-keyword" },

		{ "name": "Completion Selected Text(Inactive)", "fore": "monokai-white" },
		{ "name": "Completion Selected Matching Substring(Inactive)", "fore": "monokai-keyword" },

		{ "name": "Keyword(Access)", "fore": "monokai-constant" },
		{ "name": "Keyword(Type)", "fore": "monokai-keyword" },
		{ "name": "Keyword(Operator)", "fore": "monokai-keyword" },
		{ "name": "Keyword(Selection)", "fore": "monokai-keyword" },
		{ "name": "Keyword(Iteration)", "fore": "monokai-keyword" },
		{ "name": "Keyword(Jump)", "fore": "monokai-keyword" },
		{ "name": "Keyword(Context)", "fore": "monokai-keyword" },
		{ "name": "Keyword(Exception)", "fore": "monokai-keyword" },
		{ "name": "Keyword(Modifiers)", "fore": "monokai-keyword" },
		{ "name": "Keyword(Constants)", "fore": "monokai-constant" },
		{ "name": "Keyword(Void)", "fore": "monokai-keyword" },
		{ "name": "Keyword(Namespace)", "fore": "monokai-keyword" },
		{ "name": "Keyword(Property)", "fore": "monokai-keyword" },
		{ "name": "Keyword(Declaration)", "fore": "monokai-keyword" },
		{ "name": "Keyword(Parameter)", "fore": "monokai-keyword" },
		{ "name": "Keyword(Operator Declaration)", "fore": "monokai-keyword" },
		{ "name": "Keyword(Other)", "fore": "monokai-keyword" },

		{ "name": "User Types", "fore": "monokai-type" },
		{ "name": "User Types(Enums)", "fore": "monokai-type" },
		{ "name": "User Types(Interfaces)", "fore": "monokai-type" },
		{ "name": "User Types(Delegates)", "fore": "monokai-type" },
		{ "name": "User Types(Value types)", "fore": "monokai-type" },
		{ "name": "User Types(Type parameters)", "fore": "monokai-type" },
		{ "name": "User Types(Mutable)", "fore": "#ffd21c" },

		{ "name": "User Field Usage", "fore": "#2EE2A6" },
		{ "name": "User Field Declaration", "fore": "#2EE2A6" },

		{ "name": "User Property Usage", "fore": "#2EE2A6" },
		{ "name": "User Property Declaration", "fore": "#2EE2A6" },

		{ "name": "User Event Usage", "fore": "#FFAE81" },
		{ "name": "User Event Declaration", "fore": "#FFAE81" },

		{ "name": "User Method Usage", "fore": "monokai-functionargument" },
		{ "name": "User Method Declaration", "fore": "monokai-functionargument" },

		{ "name": "User Parameter Usage", "fore": "monokai-white" },
		{ "name": "User Parameter Declaration", "fore": "monokai-white" },

		{ "name": "User Variable Usage", "fore": "monokai-white" },
		{ "name": "User Variable Declaration", "fore": "monokai-white" },

		{ "name": "Syntax Error", "fore": "monokai-invalid", "back": "monokai-invalidBackground" },

		{ "name": "String Format Items", "fore": "monokai-white" },

		{ "name": "Breakpoint Text", "fore": "white", "back": "#6f3535" },

		{ "name": "Debugger Current Statement", "fore": "white", "back": "#69684c" },
		{ "name": "Debugger Stack Line", "fore": "white", "back": "#5c6b4d" },

		{ "name": "Diff Line(Added)", "fore": "#008A8B" },
		{ "name": "Diff Line(Removed)", "fore": "line-removed" },
		{ "name": "Diff Line(Changed)", "fore": "line-changed" },
		{ "name": "Diff Header", "fore": "#008000", "weight": "bold" },
		{ "name": "Diff Header(Separator)", "fore": "#0000FF", "weight": "bold" },
		{ "name": "Diff Header(Old)", "fore": "#008000", "weight": "bold" },
		{ "name": "Diff Header(New)", "fore": "#008000", "weight": "bold" },
		{ "name": "Diff Location", "fore": "#FB8B00", "weight": "bold" },

		{ "name": "Preview Diff Removed Line", "fore": "#5c2c2c", "back": "#dcb4b4" },
		{ "name": "Preview Diff Added Line", "fore": "#235423", "back": "#a4d9a4" },

		{ "name": "Css Comment", "fore": "monokai-comment", "weight": "bold" },
		{ "name": "Css Property Name", "fore": "monokai-white", "weight": "bold" },
		{ "name": "Css Property Value", "fore": "monokai-string", "weight": "bold" },
		{ "name": "Css Selector", "fore": "monokai-comment", "weight": "bold" },
		{ "name": "Css Keyword", "fore": "monokai-keyword", "weight": "bold" },

		{ "name": "Script Comment", "fore": "monokai-comment" },
		{ "name": "Script Keyword", "fore": "monokai-keyword" },
		{ "name": "Script Number", "fore": "monokai-constant" },
		{ "name": "Script String", "fore": "monokai-string" }
	]
}
