<Addin id          = "LuaBinding"
       namespace   = "MonoDevelop"
       name        = "Lua Language Binding"
       author      = "Mike Krüger"
       copyright   = "MIT X11"
       url         = "http://www.monodevelop.com"
       description = "Lua Language Binding"
       category    = "Language bindings"
       version     = "4.0">

	<Runtime>
		<Import assembly = "LuaBinding.dll"/>
	</Runtime>

	<Dependencies>
		<Addin id="Core" version="4.0"/>
		<Addin id="Ide" version="4.0"/>
	</Dependencies>

	<Extension path = "/MonoDevelop/Ide/FileFilters">
		<FileFilter id = "Lua"
		            insertbefore = "AllFiles"
		            _label = "Lua Files"
		            extensions = "*.lua"/>
	</Extension>

	<Extension path = "/MonoDevelop/Ide/FileTemplates">
		<FileTemplate id = "EmptyLuaFile" resource = "EmptyLuaFile.xft.xml"/>
	</Extension>

	<Extension path = "/MonoDevelop/Ide/ProjectTemplates">
		<ProjectTemplate id = "WowAddin" resource = "WowAddinProject.xpt.xml"/>
	</Extension>


	<Extension path = "/MonoDevelop/ProjectModel/LanguageBindings">
		<LanguageBinding id = "Lua" supportedextensions = ".lua" class = "LuaBinding.LuaLanguageBinding" />
	</Extension>

	<Extension path = "/MonoDevelop/ProjectModel/MSBuildItemTypes">
		<DotNetProject
			language="Lua"
			extension="luaproj"
			guid="{B4EC64DC-6D44-22EE-BBA0-C4A155D89593}" />
	</Extension>

	<Extension path = "/MonoDevelop/ProjectModel/SerializableClasses">
		<DataType class = "LuaBinding.LuaCompilerParameters" />
	</Extension>

</Addin>
